smartclip/__init__.py
smartclip/_lazy.py
smartclip/py.typed
smartclip/backends/__init__.py
smartclip/backends/jax/__init__.py
smartclip/backends/jax/integrate.py
smartclip/backends/tf/__init__.py
smartclip/backends/tf/integrate.py
smartclip/backends/torch/__init__.py
smartclip/backends/torch/integrate.py
smartclip/core/__init__.py
smartclip/core/agc.py
smartclip/core/autoclip.py
smartclip/core/clipper_base.py
smartclip/core/grouping.py
smartclip/core/stats.py
smartclip/core/types.py
smartclip/core/utils.py
smartclip/core/zscore.py
smartclip-0.1.1.dist-info/METADATA
smartclip-0.1.1.dist-info/WHEEL
smartclip-0.1.1.dist-info/licenses/LICENSE
smartclip-0.1.1.dist-info/RECORD
