Metadata-Version: 2.4
Name: smartclip
Version: 0.1.1
Summary: Adaptive gradient clipping for PyTorch, TensorFlow, and JAX
Project-URL: Homepage, https://github.com/stefangordon/smartclip
Project-URL: Issues, https://github.com/stefangordon/smartclip/issues
Author: SmartClip Maintainers
License: MIT
License-File: LICENSE
Classifier: License :: OSI Approved :: MIT License
Classifier: Programming Language :: Python
Classifier: Programming Language :: Python :: 3
Classifier: Programming Language :: Python :: 3 :: Only
Classifier: Programming Language :: Python :: 3.9
Classifier: Programming Language :: Python :: 3.10
Classifier: Programming Language :: Python :: 3.11
Classifier: Programming Language :: Python :: 3.12
Classifier: Programming Language :: Python :: 3.13
Classifier: Typing :: Typed
Requires-Python: >=3.9
Provides-Extra: bench
Requires-Dist: cycler>=0.12; extra == 'bench'
Requires-Dist: kiwisolver==1.4.7; extra == 'bench'
Requires-Dist: matplotlib>=3.8; extra == 'bench'
Requires-Dist: python-dateutil>=2.8; extra == 'bench'
Provides-Extra: dev
Requires-Dist: build>=1.2; extra == 'dev'
Requires-Dist: mypy>=1.10; extra == 'dev'
Requires-Dist: pre-commit>=3.7; extra == 'dev'
Requires-Dist: ruff>=0.6; extra == 'dev'
Requires-Dist: types-setuptools; extra == 'dev'
Provides-Extra: docs
Requires-Dist: mkdocs-material>=9.5; extra == 'docs'
Requires-Dist: mkdocs>=1.6; extra == 'docs'
Requires-Dist: mkdocstrings[python]>=0.25; extra == 'docs'
Provides-Extra: jax
Requires-Dist: flax>=0.8; extra == 'jax'
Requires-Dist: optax>=0.2; extra == 'jax'
Provides-Extra: test
Requires-Dist: hypothesis>=6; extra == 'test'
Requires-Dist: numpy>=1.26; extra == 'test'
Requires-Dist: pytest-cov>=5; extra == 'test'
Requires-Dist: pytest-randomly>=3; extra == 'test'
Requires-Dist: pytest-timeout>=2; extra == 'test'
Requires-Dist: pytest-xdist>=3; extra == 'test'
Requires-Dist: pytest>=8; extra == 'test'
Provides-Extra: tf
Provides-Extra: torch
Requires-Dist: pytorch-lightning<3,>=2.3; extra == 'torch'
Requires-Dist: transformers<5,>=4.42; extra == 'torch'
